{
  "FilePath": "c:\\Users\\Fabian\\Desktop\\Dojo-Assignments\\C#\\ASP.NET\\Dojo_Survey\\Dojo_Survey.csproj",
  "Configuration": {
    "ConfigurationName": "MVC-2.1",
    "LanguageVersion": "2.1",
    "Extensions": [
      {
        "ExtensionName": "MVC-2.1"
      }
    ]
  },
  "ProjectWorkspaceState": {
    "TagHelpers": [],
    "CSharpLanguageVersion": 703
  },
  "RootNamespace": "Dojo_Survey",
  "Documents": [
    {
      "FilePath": "c:\\Users\\Fabian\\Desktop\\Dojo-Assignments\\C#\\ASP.NET\\Dojo_Survey\\Views\\_ViewImports.cshtml",
      "TargetPath": "Views\\_ViewImports.cshtml",
      "FileKind": "mvc"
    },
    {
      "FilePath": "c:\\Users\\Fabian\\Desktop\\Dojo-Assignments\\C#\\ASP.NET\\Dojo_Survey\\Views\\Home\\Info.cshtml",
      "TargetPath": "Views\\Home\\Info.cshtml",
      "FileKind": "mvc"
    },
    {
      "FilePath": "c:\\Users\\Fabian\\Desktop\\Dojo-Assignments\\C#\\ASP.NET\\Dojo_Survey\\Views\\Home\\index.cshtml",
      "TargetPath": "Views\\Home\\index.cshtml",
      "FileKind": "mvc"
    }
  ],
  "SerializationFormat": "0.2"
}